browserfetch/__init__.py
browserfetch/__main__.py
browserfetch/browserfetch.egg-info/PKG-INFO
browserfetch/browserfetch.egg-info/SOURCES.txt
browserfetch/browserfetch.egg-info/dependency_links.txt
browserfetch/browserfetch.egg-info/not-zip-safe
browserfetch/browserfetch.egg-info/requires.txt
browserfetch/browserfetch.egg-info/top_level.txt
browserfetch/browserfetch.js
browserfetch-0.15.0.dist-info/WHEEL
browserfetch-0.15.0.dist-info/METADATA
browserfetch-0.15.0.dist-info/RECORD
