Metadata-Version: 2.3
Name: browserfetch
Version: 0.15.0
Summary: fetch in Python using your browser!
Keywords: browser,fetch,python,cookies
License: GNU General Public License v3 (GPLv3)
Classifier: License :: OSI Approved :: GNU General Public License v3 (GPLv3)
Requires-Dist: aiohttp
Requires-Dist: pyperclip
Requires-Dist: cyclopts
Requires-Python: >=3.13
Project-URL: Homepage, https://github.com/5j9/browserfetch
